include_by_ajax/__init__.py
include_by_ajax/__init__.pyc
include_by_ajax/apps.py
include_by_ajax/apps.pyc
include_by_ajax/__pycache__/__init__.cpython-311.pyc
include_by_ajax/__pycache__/__init__.cpython-36.pyc
include_by_ajax/__pycache__/__init__.cpython-37.pyc
include_by_ajax/__pycache__/apps.cpython-311.pyc
include_by_ajax/__pycache__/apps.cpython-36.pyc
include_by_ajax/__pycache__/apps.cpython-37.pyc
include_by_ajax/static/include_by_ajax/js/include_by_ajax.js
include_by_ajax/static/include_by_ajax/js/include_by_ajax.min.js
include_by_ajax/templates/include_by_ajax/includes/placeholder.html
include_by_ajax/templatetags/__init__.py
include_by_ajax/templatetags/__init__.pyc
include_by_ajax/templatetags/include_by_ajax_tags.py
include_by_ajax/templatetags/include_by_ajax_tags.pyc
include_by_ajax/templatetags/__pycache__/__init__.cpython-311.pyc
include_by_ajax/templatetags/__pycache__/__init__.cpython-36.pyc
include_by_ajax/templatetags/__pycache__/__init__.cpython-37.pyc
include_by_ajax/templatetags/__pycache__/include_by_ajax_tags.cpython-311.pyc
include_by_ajax/templatetags/__pycache__/include_by_ajax_tags.cpython-36.pyc
include_by_ajax/templatetags/__pycache__/include_by_ajax_tags.cpython-37.pyc
include_by_ajax/tests/.DS_Store
include_by_ajax/tests/__init__.py
include_by_ajax/tests/test_templatetags.py
include_by_ajax/tests/__pycache__/__init__.cpython-311.pyc
include_by_ajax/tests/__pycache__/test_templatetags.cpython-311.pyc
django_include_by_ajax-3.0.2.dist-info/AUTHORS.md
django_include_by_ajax-3.0.2.dist-info/LICENSE.md
django_include_by_ajax-3.0.2.dist-info/METADATA
django_include_by_ajax-3.0.2.dist-info/WHEEL
django_include_by_ajax-3.0.2.dist-info/top_level.txt
django_include_by_ajax-3.0.2.dist-info/RECORD
